clipper_sdk.py
clipper_sdk-0.0.4.dist-info/METADATA
clipper_sdk-0.0.4.dist-info/WHEEL
clipper_sdk-0.0.4.dist-info/top_level.txt
clipper_sdk-0.0.4.dist-info/RECORD
