Metadata-Version: 2.1
Name: clipper-sdk
Version: 0.0.4
Summary: Python wrapper around the Clipper API client
Home-page: https://github.com/ClipperData-IT/API_documentation
Author: ClipperData
Author-email: support@clipperdata.com
License: UNKNOWN
Platform: UNKNOWN
Requires-Python: >=3.7
Requires-Dist: colorama
Requires-Dist: pandas
